pywebhdfs/__init__.py
pywebhdfs/errors.py
pywebhdfs/operations.py
pywebhdfs/webhdfs.py
pywebhdfsme/__init__.py
pywebhdfsme/errors.py
pywebhdfsme/operations.py
pywebhdfsme/webhdfs.py
tests/__init__.py
tests/test_errors.py
tests/test_webhdfs.py
pywebhdfsme-0.0.7.dist-info/AUTHORS
pywebhdfsme-0.0.7.dist-info/LICENSE
pywebhdfsme-0.0.7.dist-info/METADATA
pywebhdfsme-0.0.7.dist-info/WHEEL
pywebhdfsme-0.0.7.dist-info/pbr.json
pywebhdfsme-0.0.7.dist-info/top_level.txt
pywebhdfsme-0.0.7.dist-info/RECORD
