Metadata-Version: 2.1
Name: pywebhdfsme
Version: 0.0.7
Summary: Python wrapper for the Hadoop WebHDFS REST API
Home-page: https://github.com/levinqdl/pywebhdfs/
Author: Qu Delin
Author-email: levinqdl@magicengine.com.cn
License: UNKNOWN
Platform: UNKNOWN
Classifier: Intended Audience :: Information Technology
Classifier: Intended Audience :: Developers
Classifier: License :: OSI Approved :: Apache Software License
Classifier: Operating System :: POSIX :: Linux
Classifier: Programming Language :: Python
Classifier: Programming Language :: Python :: 2
Classifier: Programming Language :: Python :: 2.7
Classifier: Programming Language :: Python :: 3.4
